mcap_logger/__init__.py
mcap_logger/mcap_handler.py
mcap_logger/topic_logger.py
mcap_logger-1.0.0.dist-info/LICENSE
mcap_logger-1.0.0.dist-info/METADATA
mcap_logger-1.0.0.dist-info/WHEEL
mcap_logger-1.0.0.dist-info/top_level.txt
mcap_logger-1.0.0.dist-info/RECORD
