Metadata-Version: 2.1
Name: mcap-logger
Version: 1.0.0
Summary: provides a standardised, easy to import and use logging method with mcap
Author-email: Kristof Kovacs <kristof.kovacs1996@gmail.com>
License: MIT License
Project-URL: Homepage, https://github.com/8-bit-hunters/mcap_logger
Project-URL: Documentation, https://8-bit-hunters.github.io/mcap_logger/
Requires-Python: >=3.12
License-File: LICENSE
Requires-Dist: foxglove-schemas-protobuf>=0.2.1
Requires-Dist: mcap-protobuf-support>=0.5.1
Requires-Dist: mkdocs-glightbox>=0.4.0
